MaterialDjango-0.2.dist-info/WHEEL
MaterialDjango-0.2.dist-info/DESCRIPTION.rst
MaterialDjango-0.2.dist-info/metadata.json
MaterialDjango-0.2.dist-info/top_level.txt
MaterialDjango-0.2.dist-info/RECORD
MaterialDjango-0.2.dist-info/METADATA
materialdjango/tests.py
materialdjango/__init__.py
materialdjango/widgets.py
materialdjango/forms.py
materialdjango/templatetags/__init__.py
materialdjango/templatetags/polymerdep.py
materialdjango/management/__init__.py
materialdjango/management/commands/__init__.py
materialdjango/management/commands/vulcanize.py
materialdjango/management/commands/phower.py
materialdjango/static/materialdjango/paper-button-submit.html
materialdjango/static/materialdjango/components/bower_components/iron-component-page/.bower.json
materialdjango/static/materialdjango/components/bower_components/iron-component-page/index.html
materialdjango/static/materialdjango/components/bower_components/iron-component-page/iron-component-page.html
materialdjango/static/materialdjango/components/bower_components/iron-component-page/README.md
materialdjango/static/materialdjango/components/bower_components/iron-component-page/.gitignore
materialdjango/static/materialdjango/components/bower_components/iron-component-page/iron-component-page.css
materialdjango/static/materialdjango/components/bower_components/iron-component-page/bower.json
materialdjango/static/materialdjango/components/bower_components/iron-component-page/test/index.html
materialdjango/static/materialdjango/components/bower_components/iron-component-page/test/test-element.html
materialdjango/static/materialdjango/components/bower_components/iron-component-page/test/iron-component-page.html
materialdjango/static/materialdjango/components/bower_components/iron-component-page/demo/json-descriptor.json
materialdjango/static/materialdjango/components/bower_components/iron-component-page/demo/index.html
materialdjango/static/materialdjango/components/bower_components/paper-radio-group/.bower.json
materialdjango/static/materialdjango/components/bower_components/paper-radio-group/index.html
materialdjango/static/materialdjango/components/bower_components/paper-radio-group/hero.svg
