Metadata-Version: 2.0
Name: MaterialDjango
Version: 0.2
Summary: A Django library bringing paper-ui and iron polymer elements to django
Home-page: https://github.com/Colorless-Green-Ideas/MaterialDjango
Author: Jack Laxson
Author-email: jack@getpizza.cat
License: MIT
Keywords: polymer paper-ui material design widgets theme
Platform: UNKNOWN
Classifier: License :: OSI Approved :: MIT License
Classifier: Intended Audience :: Developers
Classifier: Development Status :: 3 - Alpha
Classifier: Framework :: Django
Classifier: Topic :: Text Processing :: Markup :: HTML
Classifier: Topic :: Internet :: WWW/HTTP :: Dynamic Content
Classifier: Programming Language :: Python :: 2
Requires-Dist: django
